estaty/__init__.py
estaty/actions.py
estaty/analysis/__init__.py
estaty/analysis/action.py
estaty/analysis/stages/__init__.py
estaty/analysis/stages/area.py
estaty/analysis/stages/distance.py
estaty/analysis/stages/extend_clarification.py
estaty/api/__init__.py
estaty/api/estaty_api.py
estaty/api_utils/__init__.py
estaty/api_utils/area.py
estaty/api_utils/property.py
estaty/constants.py
estaty/data/__init__.py
estaty/data/action_merging.py
estaty/data/data.py
estaty/data_source/__init__.py
estaty/data_source/action.py
estaty/data_source/convert/__init__.py
estaty/data_source/load/__init__.py
estaty/data_source/load/landsat_raster.py
estaty/data_source/load/osm_save_load.py
estaty/data_source/load/osm_vector.py
estaty/data_source/load/osm_vector_utils.py
estaty/data_source/load/repository/__init__.py
estaty/data_source/load/repository/osm_tags.py
estaty/data_source/load/vector_csv.py
estaty/data_source/load/vector_gpkg.py
estaty/engine/__init__.py
estaty/engine/raster/__init__.py
estaty/engine/vector/__init__.py
estaty/engine/vector/clip.py
estaty/engine/vector/convert.py
estaty/engine/vector/crop.py
estaty/engine/vector/extract/__init__.py
estaty/engine/vector/extract/osm_nodes.py
estaty/engine/vector/point/__init__.py
estaty/engine/vector/point/distance.py
estaty/engine/vector/points_representation/__init__.py
estaty/engine/vector/points_representation/to_point.py
estaty/engine/vector/points_representation/to_points_reduce/__init__.py
estaty/engine/vector/points_representation/to_points_reduce/common.py
estaty/engine/vector/points_representation/to_points_reduce/line.py
estaty/engine/vector/points_representation/to_points_reduce/point.py
estaty/engine/vector/points_representation/to_points_reduce/polygon.py
estaty/experiment/__init__.py
estaty/experiment/administrative.py
estaty/experiment/explore.py
estaty/main.py
estaty/merge/__init__.py
estaty/merge/action.py
estaty/merge/vector_merge.py
estaty/paths.py
estaty/preprocessing/__init__.py
estaty-0.1.0.dist-info/METADATA
estaty-0.1.0.dist-info/WHEEL
estaty-0.1.0.dist-info/RECORD
